setup.py
Products/__init__.py
Products.upaCore.egg-info/PKG-INFO
Products.upaCore.egg-info/SOURCES.txt
Products.upaCore.egg-info/dependency_links.txt
Products.upaCore.egg-info/namespace_packages.txt
Products.upaCore.egg-info/not-zip-safe
Products.upaCore.egg-info/requires.txt
Products.upaCore.egg-info/top_level.txt
Products/upaCore/README.txt
Products/upaCore/__init__.py
Products/upaCore/config.py
Products/upaCore/configure.zcml
Products/upaCore/fss.zcml
Products/upaCore/header.txt
Products/upaCore/permissions.py
Products/upaCore/permissions.zcml
Products/upaCore/profiles.zcml
Products/upaCore/setuphandlers.py
Products/upaCore/version.txt
Products/upaCore/viewlets.zcml
Products/upaCore/Extensions/Install.py
Products/upaCore/Extensions/__init__.py
Products/upaCore/Extensions/gensite.py
Products/upaCore/browser/__init__.py
Products/upaCore/browser/configure.zcml
Products/upaCore/browser/misc.py
Products/upaCore/content/__init__.py
Products/upaCore/content/memberinfo.py
Products/upaCore/data/audiences.txt
Products/upaCore/data/news-remote-servers.txt
Products/upaCore/extenders/__init__.py
Products/upaCore/i18n/upacore-de.po
Products/upaCore/profiles/default/actions.xml
Products/upaCore/profiles/default/catalog.xml
Products/upaCore/profiles/default/cssregistry.xml
Products/upaCore/profiles/default/import_steps.xml
Products/upaCore/profiles/default/mailhost.xml
Products/upaCore/profiles/default/portal_languages.xml
Products/upaCore/profiles/default/portlets.xml
Products/upaCore/profiles/default/rolemap.xml
Products/upaCore/profiles/default/skins.xml
Products/upaCore/profiles/default/types.xml
Products/upaCore/profiles/default/upacore_various.txt
Products/upaCore/profiles/default/viewlets.xml
Products/upaCore/profiles/default/types/MemberInfo.xml
Products/upaCore/profiles/dependencies/metadata.xml
Products/upaCore/skins/upaCore/cleanupMembers.xpy
Products/upaCore/skins/upaCore/logged_in.cpy
Products/upaCore/skins/upaCore/logged_in.cpy.metadata
Products/upaCore/skins/upaCore/portlet_upa_memberinfo.pt
Products/upaCore/skins/upaCore/upaAddMemberInfo.py
Products/upaCore/skins/upaCore/upaCore.css.dtml
Products/upaCore/skins/upaCore/upaHasMemberInfo.py
Products/upaCore/skins/upaCore/upaMemberExport.xpy
Products/upaCore/skins/upaCore/upaMemberImport.pt
