Metadata-Version: 1.0
Name: Products.upaCore
Version: 0.5.1.1
Summary: Member info implementation for the GermanUPA
Home-page: http://pypi.python.org/pypi/Products.upaCore
Author: Andreas Jung
Author-email: info@zopyx.com
License: GPL
Platform: UNKNOWN
Classifier: Programming Language :: Python
Classifier: Framework :: Zope2
Classifier: Framework :: Plone
